Metadata-Version: 2.1
Name: palladium-python
Version: 1.0.1
Summary: Common utility functions.
Home-page: https://github.com/siddhantkushwaha/palladium
Author: Siddhant Kushwaha
Author-email: k16.siddhant@gmail.com
License: MIT
Download-URL: https://github.com/siddhantkushwaha/palladium/archive/1.0.1.tar.gz
Keywords: CHROMIUM,SELENIUM,AUTOMATION,TESTING
Platform: UNKNOWN
Classifier: Development Status :: 3 - Alpha
Classifier: Intended Audience :: Developers
Classifier: Topic :: Software Development :: Build Tools
Classifier: License :: OSI Approved :: MIT License
Classifier: Programming Language :: Python :: 3.6
Classifier: Programming Language :: Python :: 3.7
Classifier: Programming Language :: Python :: 3.8
Classifier: Programming Language :: Python :: 3.9
License-File: LICENSE
